_bomf_version.py
bomf/__init__.py
bomf/config.py
bomf/py.typed
bomf/filter/__init__.py
bomf/filter/sourcedataproviderfilter.py
bomf/loader/__init__.py
bomf/loader/entityloader.py
bomf/logging/__init__.py
bomf/mapper/__init__.py
bomf/model/__init__.py
bomf/provider/__init__.py
bomf-0.11.3.dist-info/METADATA
bomf-0.11.3.dist-info/WHEEL
bomf-0.11.3.dist-info/licenses/LICENSE
bomf-0.11.3.dist-info/RECORD
