Metadata-Version: 2.3
Name: bomf
Version: 0.11.3
Summary: BO4E Migration Framework
Project-URL: Changelog, https://github.com/Hochfrequenz/bo4e_migration_framework/releases
Project-URL: Homepage, https://github.com/Hochfrequenz/bo4e_migration_framework
Author-email: Hochfrequenz Unternehmensberatung GmbH <info@hochfrequenz.de>
License: MIT
License-File: LICENSE
Keywords: BO4E,Data,Migration
Classifier: Development Status :: 4 - Beta
Classifier: Environment :: Console
Classifier: Intended Audience :: Developers
Classifier: License :: OSI Approved :: MIT License
Classifier: Operating System :: OS Independent
Classifier: Programming Language :: Python
Classifier: Programming Language :: Python :: 3 :: Only
Classifier: Programming Language :: Python :: 3.11
Classifier: Programming Language :: Python :: 3.12
Requires-Python: >=3.11
Requires-Dist: bidict
Requires-Dist: frozendict
Requires-Dist: injector
Requires-Dist: networkx
Requires-Dist: pvframework
Requires-Dist: pydantic>=2.0.0
Requires-Dist: python-generics
Requires-Dist: typeguard
Provides-Extra: coverage
Requires-Dist: coverage==7.6.1; extra == 'coverage'
Provides-Extra: dev
Requires-Dist: pip-tools; extra == 'dev'
Provides-Extra: formatting
Requires-Dist: black==24.8.0; extra == 'formatting'
Requires-Dist: isort==5.13.2; extra == 'formatting'
Provides-Extra: linting
Requires-Dist: pylint==3.2.7; extra == 'linting'
Provides-Extra: spellcheck
Requires-Dist: codespell==2.3.0; extra == 'spellcheck'
Provides-Extra: test-packaging
Requires-Dist: build==1.2.2; extra == 'test-packaging'
Requires-Dist: twine==5.1.1; extra == 'test-packaging'
Provides-Extra: tests
Requires-Dist: bo4e==202401.2.1; extra == 'tests'
Requires-Dist: pytest-asyncio==0.24.0; extra == 'tests'
Requires-Dist: pytest==8.3.3; extra == 'tests'
Provides-Extra: type-check
Requires-Dist: mypy==1.11.2; extra == 'type-check'
Requires-Dist: networkx-stubs==0.0.1; extra == 'type-check'
Requires-Dist: types-frozendict==2.0.9; extra == 'type-check'
